nrp_devtools/__init__.py
nrp_devtools/copier_extensions.py
nrp_devtools/main.py
nrp_devtools/x509.py
nrp_devtools/cli/__init__.py
nrp_devtools/cli/alembic.py
nrp_devtools/cli/base.py
nrp_devtools/cli/build.py
nrp_devtools/cli/check.py
nrp_devtools/cli/develop.py
nrp_devtools/cli/image.py
nrp_devtools/cli/initialize.py
nrp_devtools/cli/model.py
nrp_devtools/cli/run.py
nrp_devtools/cli/translations.py
nrp_devtools/cli/ui.py
nrp_devtools/cli/upgrade.py
nrp_devtools/cli/watch.py
nrp_devtools/commands/__init__.py
nrp_devtools/commands/alembic.py
nrp_devtools/commands/build.py
nrp_devtools/commands/check.py
nrp_devtools/commands/check_old.py
nrp_devtools/commands/db.py
nrp_devtools/commands/docker.py
nrp_devtools/commands/forks.py
nrp_devtools/commands/invenio.py
nrp_devtools/commands/opensearch.py
nrp_devtools/commands/pyproject.py
nrp_devtools/commands/s3.py
nrp_devtools/commands/types.py
nrp_devtools/commands/utils.py
nrp_devtools/commands/uv.py
nrp_devtools/commands/develop/__init__.py
nrp_devtools/commands/develop/controller.py
nrp_devtools/commands/develop/runner.py
nrp_devtools/commands/model/__init__.py
nrp_devtools/commands/model/compile.py
nrp_devtools/commands/ui/__init__.py
nrp_devtools/commands/ui/assets.py
nrp_devtools/commands/ui/build.py
nrp_devtools/commands/ui/create.py
nrp_devtools/commands/ui/create_detail.py
nrp_devtools/commands/ui/less.py
nrp_devtools/commands/ui/link_assets.py
nrp_devtools/commands/ui/translations.py
nrp_devtools/config/__init__.py
nrp_devtools/config/config.py
nrp_devtools/config/enums.py
nrp_devtools/config/i18n_config.py
nrp_devtools/config/model_config.py
nrp_devtools/config/repository_config.py
nrp_devtools/config/ui_config.py
nrp_devtools/config/wizard.py
nrp_devtools/templates/component.less
nrp_devtools/templates/ui_page/cookiecutter.json
nrp_devtools/templates/ui_page/{{cookiecutter.name}}/__init__.py
nrp_devtools/templates/ui_page/{{cookiecutter.name}}/templates/{{cookiecutter.template_name}}.jinja
nrp_devtools-12.0.4.dist-info/METADATA
nrp_devtools-12.0.4.dist-info/WHEEL
nrp_devtools-12.0.4.dist-info/entry_points.txt
nrp_devtools-12.0.4.dist-info/top_level.txt
nrp_devtools-12.0.4.dist-info/RECORD
