Metadata-Version: 2.4
Name: nrp-devtools
Version: 12.0.4
Summary: NRP repository development tools
Author-email: Miroslav Simek <miroslav.simek@cesnet.cz>
Requires-Python: <3.13,>=3.12
Requires-Dist: setuptools
Requires-Dist: pip
Requires-Dist: wheel
Requires-Dist: click
Requires-Dist: aenum
Requires-Dist: pydash
Requires-Dist: PyYAML
Requires-Dist: dacite
Requires-Dist: ruamel.yaml
Requires-Dist: case-converter
Requires-Dist: cryptography
Requires-Dist: copier
Requires-Dist: copier_templates_extensions
Requires-Dist: pycountry
Requires-Dist: uv
Requires-Dist: tomli
Requires-Dist: tomli-w
Requires-Dist: requirements-parser
Requires-Dist: tqdm
Requires-Dist: watchdog
Requires-Dist: psutil
Requires-Dist: oarepo-tools
Requires-Dist: minio
Requires-Dist: redis
Requires-Dist: psycopg[binary]
Requires-Dist: pika
Requires-Dist: opensearch-py
Requires-Dist: pytest
Requires-Dist: oarepo-tools
Requires-Dist: flask
Requires-Dist: lxml
